{"otmonitor":{"flamestatus":{"value":"Off","unit":"","epoch":22908},"chmodus":{"value":"Off","unit":"","epoch":22908},"chenable":{"value":"On","unit":"","epoch":22908},"ch2modus":{"value":"Off","unit":"","epoch":22908},"ch2enable":{"value":"Off","unit":"","epoch":22908},"dhwmode":{"value":"Off","unit":"","epoch":22908},"dhwenable":{"value":"Off","unit":"","epoch":22908},"diagnosticindicator":{"value":"Off","unit":"","epoch":22908},"faultindicator":{"value":"Off","unit":"","epoch":22908},"coolingmodus":{"value":"Off","unit":"","epoch":22908},"coolingactive":{"value":"Off","unit":"","epoch":22908},"otcactive":{"value":"Off","unit":"","epoch":22908},"controlsetpoint":{"value":45,"unit":"°C","epoch":22878},"sensorsimulation":{"value":false,"unit":"","epoch":1782792082}}}