{"enabled":false,"active":false,"control_mode":0,"boiler_status":"off","target_temp":20,"room_temp":null,"outside_temp":null,"heating_curve":0,"pid_output":0,"final_setpoint":null,"error":0,"pid_p":0,"pid_i":0,"pid_d":0,"kp":0,"ki":0,"kd":0,"raw_derivative":0,"coefficient":1.5,"deadband":0.1,"overshoot_margin":3,"cycle_count":0,"cycles_this_hour":0,"last_cycle_class":0,"cycle_max_flow":0,"cycle_overshoot_sec":0,"duty_ratio":0,"overshoot_fraction":0,"underheat_fraction":0,"cycle_phase":"idle","phase_duration_sec":0,"pwm_duty":0,"pwm_flame_req":false,"active_preset":0,"mod_suppressed":false,"dhw_active":false,"dhw_setpoint":0,"dhw_config_tank":false,"dhw_enable":true,"control_interval_sec":30,"fallback_active":false,"fallback_reason":0,"max_rel_modulation":100,"current_modulation":100,"heating_system":0,"heating_source":0,"heating_source_detected":1,"manufacturer":"Remeha","manufacturer_setting":0,"manufacturer_detected":13,"slave_memberid":11,"max_setpoint_system":62,"external_temp_valid":false,"external_outdoor_valid":false,"pv_surplus_w":0,"pv_surplus_valid":false,"pv_boost_active":false,"pv_boost_applied_c":0,"pv_boost_enabled":false,"safety_tripped":false,"valves_open":true,"window_open":false,"window_detection":false,"push_setpoint":false,"flame_off_offset":18,"force_pwm":false,"flow_offset":2,"pressure":0,"pressure_drop_rate":0,"pressure_alarm":false,"modulation_reliable":true,"setpoint_mismatch":false,"curve_recommendation":"insufficient","heating_curve_recommendation":"insufficient","mean_error":0,"error_stddev":0,"target_temp_step":0.5,"power_kw":0,"energy_kwh":0,"boiler_capacity":24,"boiler_rated_kw":0,"boiler_efficiency":0.92,"energy_estimated_kwh":0,"preset_sync":false,"thermal_coeff":0.05,"thermal_drop_rate":0,"thermal_model_valid":false,"estimated_room":0,"last_known_room":0,"solar_gain_active":false,"indoor_rise_rate":0,"summer_simmer":false,"summer_active":false,"summer_hours_above":0,"summer_threshold":18,"summer_min_hours":6,"comfort_adjust":false,"humidity":0,"humidity_valid":false,"comfort_offset":0,"comfort_ref_humidity":50,"comfort_max_offset":1,"simulation":false,"sim_available":true,"auto_tune":false,"auto_tune_active":false,"auto_tune_cycles":0,"auto_tune_score":0,"auto_tune_rate":0.02,"sensor_max_age":21600,"error_monitoring":false,"auto_gains_value":2,"auto_gains":true,"kp_manual":5,"ki_manual":0.0005,"kd_manual":0,"thermal_comfort":false,"heating_mode":"comfort","cycles_per_hour":3,"valve_offset":0,"solar_freeze_integral":true,"multi_area":false,"multi_area_count":0,"ble_enable":false,"ble_failover":true,"ble_failover_active":false,"ble_temp_valid":false,"ble_sensor_count":0}